randalo/__init__.py
randalo/modeling_layer.py
randalo/randalo.py
randalo/reductions.py
randalo/sklearn_integration.py
randalo/truncnorm.py
randalo/utils.py
test/__init__.py
test/test_randalo.py
test/test_reductions.py
test/test_sklearn_integration.py
test/test_truncnorm.py
test/test_utils.py
randalo-0.1.0.dist-info/LICENSE
randalo-0.1.0.dist-info/METADATA
randalo-0.1.0.dist-info/WHEEL
randalo-0.1.0.dist-info/top_level.txt
randalo-0.1.0.dist-info/RECORD
