Metadata-Version: 2.1
Name: randalo
Version: 0.1.0
Home-page: https://github.com/cvxgrp/randalo
Author: Parth Nobel
Author-email: ptnobel@stanford.edu
Classifier: Programming Language :: Python :: 3
License-File: LICENSE
Requires-Dist: numpy>=1.17.5
Requires-Dist: scipy
Requires-Dist: torch
Requires-Dist: torch-linops
